__init__.py
balancedtime.py
balancedtime-0.16b0.dist-info/LICENSE
balancedtime-0.16b0.dist-info/METADATA
balancedtime-0.16b0.dist-info/WHEEL
balancedtime-0.16b0.dist-info/top_level.txt
balancedtime-0.16b0.dist-info/RECORD
