Metadata-Version: 2.1
Name: balancedtime
Version: 0.16b0
Summary: Convert regular time into 12-hour days and nights
Home-page: https://github.com/Lolologist/balancedtime
Author: Daniel Bishop
Author-email: lolologist@gmail.com
License: UNKNOWN
Platform: UNKNOWN
Classifier: Programming Language :: Python :: 3
Classifier: License :: OSI Approved :: Apache Software License
Classifier: Operating System :: OS Independent
Classifier: Development Status :: 1 - Planning
Classifier: Intended Audience :: Developers
Classifier: Topic :: Scientific/Engineering :: Astronomy
Classifier: Topic :: Software Development :: Libraries :: Python Modules
Classifier: Topic :: Utilities
Requires-Dist: astral
Requires-Dist: uszipcode
